MANIFEST.in
README.rst
setup.py
collective/__init__.py
collective/__init__.pyc
collective.teaser.egg-info/PKG-INFO
collective.teaser.egg-info/SOURCES.txt
collective.teaser.egg-info/dependency_links.txt
collective.teaser.egg-info/entry_points.txt
collective.teaser.egg-info/namespace_packages.txt
collective.teaser.egg-info/not-zip-safe
collective.teaser.egg-info/requires.txt
collective.teaser.egg-info/top_level.txt
collective/teaser/__init__.py
collective/teaser/__init__.pyc
collective/teaser/config.py
collective/teaser/config.pyc
collective/teaser/configure.zcml
collective/teaser/interfaces.py
collective/teaser/interfaces.pyc
collective/teaser/subscribers.py
collective/teaser/tests.py
collective/teaser/vocabularies.py
collective/teaser/vocabularies.pyc
collective/teaser/browser/__init__.py
collective/teaser/browser/__init__.pyc
collective/teaser/browser/common.py
collective/teaser/browser/common.pyc
collective/teaser/browser/configure.zcml
collective/teaser/browser/manage_teaser_portlets.pt
collective/teaser/browser/manager.py
collective/teaser/browser/manager.pyc
collective/teaser/browser/portlet.py
collective/teaser/browser/portlet.pyc
collective/teaser/browser/teaser.pt
collective/teaser/browser/teaser_portlet.pt
collective/teaser/browser/teaser_portlet_manager_renderer.pt
collective/teaser/browser/teaser_portlets.pt
collective/teaser/browser/teaser_view.pt
collective/teaser/browser/viewlets.py
collective/teaser/browser/viewlets.pyc
collective/teaser/browser/z3cformportlet.py
collective/teaser/browser/resources/styles.css
collective/teaser/browser/resources/teaser.js
collective/teaser/browser/resources/teaser_icon.png
collective/teaser/content/__init__.py
collective/teaser/content/__init__.pyc
collective/teaser/content/teaser.py
collective/teaser/content/teaser.pyc
collective/teaser/locales/collective.teaser.pot
collective/teaser/locales/de/LC_MESSAGES/collective.teaser.mo
collective/teaser/locales/de/LC_MESSAGES/collective.teaser.po
collective/teaser/profiles/default/browserlayer.xml
collective/teaser/profiles/default/catalog.xml
collective/teaser/profiles/default/cssregistry.xml
collective/teaser/profiles/default/diff_tool.xml
collective/teaser/profiles/default/factorytool.xml
collective/teaser/profiles/default/jsregistry.xml
collective/teaser/profiles/default/metadata.xml
