Metadata-Version: 1.1
Name: collective.teaser
Version: 2.3
Summary: Teaser/Banner content type for Plone
Home-page: http://github.com/collective/collective.teaser
Author: Johannes Raggam
Author-email: raggam-nl@adm.at
License: GPL
Keywords: Plone,Teaser,Banner
Platform: UNKNOWN
Classifier: Framework :: Plone
Classifier: Programming Language :: Python
